LICENSE
deadsimple/__init__.py
deadsimple/context.py
deadsimple/exceptions.py
deadsimple/lazy.py
deadsimple/resolve.py
deadsimple-0.4.0.dist-info/LICENSE
deadsimple-0.4.0.dist-info/WHEEL
deadsimple-0.4.0.dist-info/METADATA
deadsimple-0.4.0.dist-info/RECORD
