Metadata-Version: 2.1
Name: deadsimple
Version: 0.4.0
Summary: A dependency injection library, aimed for the least amount of magic
Home-page: https://github.com/mastern2k3/deadsimple
License: MIT
Keywords: dependency_injection
Author: Nitzan Zada
Author-email: nitzan.zada@gmail.com
Requires-Python: >=3.8,<4.0
Classifier: License :: OSI Approved :: MIT License
Classifier: Programming Language :: Python :: 3
Classifier: Programming Language :: Python :: 3.10
Classifier: Programming Language :: Python :: 3.8
Classifier: Programming Language :: Python :: 3.9
Project-URL: Repository, https://github.com/mastern2k3/deadsimple
